pretty_print/__init__.py
pretty_print/colors.py
pretty_print/printer.py
aricma_pretty_print-0.0.3.dist-info/LICENSE
aricma_pretty_print-0.0.3.dist-info/METADATA
aricma_pretty_print-0.0.3.dist-info/WHEEL
aricma_pretty_print-0.0.3.dist-info/top_level.txt
aricma_pretty_print-0.0.3.dist-info/RECORD
