Metadata-Version: 2.1
Name: aricma-pretty-print
Version: 0.0.3
Summary: A small printer package to get some better looking print statements for any cli.
Home-page: https://github.com/aricma/pretty-print.git
Author: Adrian Mindak
License: UNKNOWN
Platform: UNKNOWN
Classifier: Programming Language :: Python :: 3
Classifier: License :: OSI Approved :: MIT License
Classifier: Operating System :: OS Independent
Requires-Python: >=3.6
